Metadata-Version: 1.0
Name: Ma-rin
Version: 0.1
Summary: Diagrama fasorial
Home-page: https://github.com/AMRxviii/A
Author: Anigi marín
Author-email: UNKNOWN
License: MIT
Platform: UNKNOWN
